MANIFEST.in
setup.cfg
setup.py
pygazetteer/__init__.py
pygazetteer/gaze.txt
pygazetteer/gazetteer.py
pygazetteer.egg-info/PKG-INFO
pygazetteer.egg-info/SOURCES.txt
pygazetteer.egg-info/dependency_links.txt
pygazetteer.egg-info/not-zip-safe
pygazetteer.egg-info/requires.txt
pygazetteer.egg-info/top_level.txt