Metadata-Version: 1.0
Name: pygazetteer
Version: 0.1.0
Summary: Location extractor by looking up gazetteer
Home-page: https://github.com/monkey2000/pygazetteer
Author: UNKNOWN
Author-email: UNKNOWN
License: MIT
Platform: UNKNOWN
